__init__.py
wiktionaryparser.py
tests/__init__.py
tests/context.py
tests/test.py
utils/__init__.py
utils/utils.py
wiktionaryparser-0.0.97.data/data/readme/readme.md
wiktionaryparser-0.0.97.data/data/requirements/requirements.txt
wiktionaryparser-0.0.97.data/data/testOutput/testOutput.json
wiktionaryparser-0.0.97.dist-info/METADATA
wiktionaryparser-0.0.97.dist-info/RECORD
wiktionaryparser-0.0.97.dist-info/WHEEL
wiktionaryparser-0.0.97.dist-info/top_level.txt
