Metadata-Version: 2.1
Name: wiktionaryparser
Version: 0.0.97
Summary: A tool to parse word data from wiktionary.com into a JSON object
Home-page: https://github.com/Suyash458/WiktionaryParser
Author: Suyash Behera
Author-email: sne9x@outlook.com
License: UNKNOWN
Download-URL: https://github.com/Suyash458/WiktionaryParser/archive/master.zip
Keywords: Parser,Wiktionary
Platform: UNKNOWN
Classifier: Development Status :: 5 - Production/Stable
